Metadata-Version: 2.1
Name: shellwhat-ext
Version: 0.4.1
Summary: Extensions to shellwhat testing
Home-page: https://github.com/datacamp/shellwhat_ext
Author: Michael Chow
Author-email: michael@datacamp.com
Maintainer: Filip Schouwenaars
Maintainer-email: filip@datacamp.com
License: GNU version 3
Platform: UNKNOWN
